exkaldi/__init__.py
exkaldi/error.py
exkaldi/version.py
exkaldi/config/__init__.py
exkaldi/config/compute_fbank.py
exkaldi/config/compute_mfcc.py
exkaldi/config/compute_plp.py
exkaldi/config/compute_spectrogram.py
exkaldi/config/decode_lattice.py
exkaldi/config/gmm_decode.py
exkaldi/config/nn_decode.py
exkaldi/config/train_ngrams_kenlm.py
exkaldi/config/train_ngrams_srilm.py
exkaldi/config/write_ctm.py
exkaldi/core/__init__.py
exkaldi/core/archive.py
exkaldi/core/common.py
exkaldi/core/feature.py
exkaldi/core/load.py
exkaldi/decode/__init__.py
exkaldi/decode/e2e.py
exkaldi/decode/graph.py
exkaldi/decode/score.py
exkaldi/decode/wfst.py
exkaldi/hmm/__init__.py
exkaldi/hmm/hmm.py
exkaldi/lm/__init__.py
exkaldi/lm/lm.py
exkaldi/nn/__init__.py
exkaldi/nn/nn.py
exkaldi/utils/__init__.py
exkaldi/utils/argparse.py
exkaldi/utils/declare.py
exkaldi/utils/declare_test.py
exkaldi/utils/utils.py
exkaldi/utils/utils_test.py
exkaldi-1.3.5.4.data/data/exkaldisrc/tools/build_binary
exkaldi-1.3.5.4.data/data/exkaldisrc/tools/lmplz
exkaldi-1.3.5.4.data/data/exkaldisrc/tools/prefix_beam_search_decode
exkaldi-1.3.5.4.data/data/exkaldisrc/tools/simple_beam_search_decode
exkaldi-1.3.5.4.dist-info/LICENSE
exkaldi-1.3.5.4.dist-info/METADATA
exkaldi-1.3.5.4.dist-info/WHEEL
exkaldi-1.3.5.4.dist-info/top_level.txt
exkaldi-1.3.5.4.dist-info/RECORD
