Metadata-Version: 2.1
Name: exkaldi
Version: 1.3.5.4
Summary: ExKaldi Automatic Speech Recognition Toolkit
Home-page: https://github.com/wangyu09/exkaldi
Author: Wang Yu
Author-email: wangyu@alps-lab.org
License: UNKNOWN
Platform: UNKNOWN
Classifier: Programming Language :: Python :: 3
Classifier: License :: OSI Approved :: Apache Software License
Requires-Dist: numpy (>=1.16)
